gitmen/__init__.py
gitmen/codeArt.py
gitmen/config.py
gitmen/main.py
gitmen/commands/__init__.py
gitmen/commands/angular_update.py
gitmen/commands/check_github.py
gitmen/commands/check_outdated.py
gitmen/commands/check_status.py
gitmen/commands/clone_repos.py
gitmen/commands/expo_fix.py
gitmen/commands/get_cli_version.py
gitmen/commands/ncu_update.py
gitmen/commands/projects_update.py
gitmen/commands/script.py
gitmen/translations/check_outdated.en.yml
gitmen/translations/check_outdated.pt.yml
gitmen/translations/check_status.en.yml
gitmen/translations/check_status.pt.yml
gitmen/translations/clone_repos.en.yml
gitmen/translations/clone_repos.pt.yml
gitmen/translations/comman.en.yml
gitmen/translations/comman.pt.yml
gitmen/translations/main.en.yml
gitmen/translations/main.pt.yml
gitmen/translations/ncu_update.en.yml
gitmen/translations/ncu_update.pt.yml
gitmen/translations/script.en.yml
gitmen/translations/script.pt.yml
gitmen/translations/update.en.yml
gitmen/translations/update.pt.yml
gitmen/utils/__init__.py
gitmen-0.4.2.dist-info/METADATA
gitmen-0.4.2.dist-info/WHEEL
gitmen-0.4.2.dist-info/entry_points.txt
gitmen-0.4.2.dist-info/top_level.txt
gitmen-0.4.2.dist-info/RECORD
