Metadata-Version: 2.1
Name: gitmen
Version: 0.4.2
Summary: CLI tool for managing GitHub projects, updating dependencies, and checking project statuses.
Home-page: https://github.com/lucasferreiralimax/gitmen
Author: lucasferreiralimax
Author-email: lucasferreiralimax@gmail.com
Keywords: github cli projects dependencies
Classifier: Intended Audience :: Developers
Classifier: Topic :: Software Development :: Build Tools
Classifier: Programming Language :: Python :: 3
Classifier: Operating System :: OS Independent
Classifier: Operating System :: POSIX
Classifier: Operating System :: MacOS
Classifier: Operating System :: Unix
Requires-Python: >=3.9
Requires-Dist: python-i18n[yaml]
Requires-Dist: inquirer
Requires-Dist: rich
Requires-Dist: pyperclip
Requires-Dist: requests
